opensim-3.3.data/purelib/opensim/__init__.py
opensim-3.3.data/purelib/opensim/_opensim.so
opensim-3.3.data/purelib/opensim/opensim.py
opensim-3.3.dist-info/DESCRIPTION.rst
opensim-3.3.dist-info/METADATA
opensim-3.3.dist-info/metadata.json
opensim-3.3.dist-info/RECORD
opensim-3.3.dist-info/top_level.txt
opensim-3.3.dist-info/WHEEL
