Metadata-Version: 2.0
Name: opensim
Version: 3.3
Summary: OpenSim Simulation Framework
Home-page: http://opensim.stanford.edu/
Author: OpenSim Team
Author-email: ahabib@stanford.edu
License: Apache 2.0
Platform: UNKNOWN
Classifier: Intended Audience :: Science/Research
Classifier: Operating System :: OS Independent
Classifier: Programming Language :: Python :: 2.7
Classifier: Topic :: Scientific/Engineering :: Physics
